# Chunk: d1eec2699214_2

- source: `.venv-lab/Lib/site-packages/debugpy/_vendored/pydevd/_pydevd_frame_eval/vendored/bytecode/tests/test_misc.py`
- lines: 188-259
- chunk: 3/3

```

        ).lstrip()
        self.check_dump_bytecode(code, expected, lineno=True)

    def test_concrete_bytecode(self):
        source = """
            def func(test):
                if test == 1:
                    return 1
                elif test == 2:
                    return 2
                return 3
        """
        code = disassemble(source, function=True)
        code = code.to_concrete_bytecode()

        # without line numbers
        expected = f"""
  0    LOAD_FAST 0
  2    LOAD_CONST 1
  4    COMPARE_OP 2
  6    POP_JUMP_IF_FALSE {6 if OFFSET_AS_INSTRUCTION else 12}
  8    LOAD_CONST 1
 10    RETURN_VALUE
 12    LOAD_FAST 0
 14    LOAD_CONST 2
 16    COMPARE_OP 2
 18    POP_JUMP_IF_FALSE {12 if OFFSET_AS_INSTRUCTION else 24}
 20    LOAD_CONST 2
 22    RETURN_VALUE
 24    LOAD_CONST 3
 26    RETURN_VALUE
""".lstrip("\n")
        self.check_dump_bytecode(code, expected)

        # with line numbers
        expected = f"""
L.  2   0: LOAD_FAST 0
        2: LOAD_CONST 1
        4: COMPARE_OP 2
        6: POP_JUMP_IF_FALSE {6 if OFFSET_AS_INSTRUCTION else 12}
L.  3   8: LOAD_CONST 1
       10: RETURN_VALUE
L.  4  12: LOAD_FAST 0
       14: LOAD_CONST 2
       16: COMPARE_OP 2
       18: POP_JUMP_IF_FALSE {12 if OFFSET_AS_INSTRUCTION else 24}
L.  5  20: LOAD_CONST 2
       22: RETURN_VALUE
L.  6  24: LOAD_CONST 3
       26: RETURN_VALUE
""".lstrip("\n")
        self.check_dump_bytecode(code, expected, lineno=True)

    def test_type_validation(self):
        class T:
            first_lineno = 1

        with self.assertRaises(TypeError):
            bytecode.dump_bytecode(T())


class MiscTests(unittest.TestCase):
    def skip_test_version(self):
        import setup

        self.assertEqual(bytecode.__version__, setup.VERSION)


if __name__ == "__main__":
    unittest.main()  # pragma: no cover
```
