# Chunk: d1eec2699214_1

- source: `.venv-lab/Lib/site-packages/debugpy/_vendored/pydevd/_pydevd_frame_eval/vendored/bytecode/tests/test_misc.py`
- lines: 93-199
- chunk: 2/3

```
abel = Label()
        code = Bytecode([Instr("JUMP_ABSOLUTE", label)])

        expected = "    JUMP_ABSOLUTE <error: unknown label>\n\n"
        self.check_dump_bytecode(code, expected)

    def test_blocks_broken_jump(self):
        block = BasicBlock()
        code = ControlFlowGraph()
        code[0].append(Instr("JUMP_ABSOLUTE", block))

        expected = textwrap.dedent(
            """
            block1:
                JUMP_ABSOLUTE <error: unknown block>

        """
        ).lstrip("\n")
        self.check_dump_bytecode(code, expected)

    def test_bytecode_blocks(self):
        source = """
            def func(test):
                if test == 1:
                    return 1
                elif test == 2:
                    return 2
                return 3
        """
        code = disassemble(source, function=True)
        code = ControlFlowGraph.from_bytecode(code)

        # without line numbers
        enum_repr = "<Compare.EQ: 2>"
        expected = textwrap.dedent(
            f"""
            block1:
                LOAD_FAST 'test'
                LOAD_CONST 1
                COMPARE_OP {enum_repr}
                POP_JUMP_IF_FALSE <block3>
                -> block2

            block2:
                LOAD_CONST 1
                RETURN_VALUE

            block3:
                LOAD_FAST 'test'
                LOAD_CONST 2
                COMPARE_OP {enum_repr}
                POP_JUMP_IF_FALSE <block5>
                -> block4

            block4:
                LOAD_CONST 2
                RETURN_VALUE

            block5:
                LOAD_CONST 3
                RETURN_VALUE

        """
        ).lstrip()
        self.check_dump_bytecode(code, expected)

        # with line numbers
        expected = textwrap.dedent(
            f"""
            block1:
                L.  2   0: LOAD_FAST 'test'
                        1: LOAD_CONST 1
                        2: COMPARE_OP {enum_repr}
                        3: POP_JUMP_IF_FALSE <block3>
                -> block2

            block2:
                L.  3   0: LOAD_CONST 1
                        1: RETURN_VALUE

            block3:
                L.  4   0: LOAD_FAST 'test'
                        1: LOAD_CONST 2
                        2: COMPARE_OP {enum_repr}
                        3: POP_JUMP_IF_FALSE <block5>
                -> block4

            block4:
                L.  5   0: LOAD_CONST 2
                        1: RETURN_VALUE

            block5:
                L.  6   0: LOAD_CONST 3
                        1: RETURN_VALUE

        """
        ).lstrip()
        self.check_dump_bytecode(code, expected, lineno=True)

    def test_concrete_bytecode(self):
        source = """
            def func(test):
                if test == 1:
                    return 1
                elif test == 2:
                    return 2
```
